nd_sim/__init__.py
nd_sim/fingerprint.py
nd_sim/pca_tranform.py
nd_sim/pre_processing.py
nd_sim/similarity.py
nd_sim/utils.py
tests/__init__.py
tests/test_fingerprint.py
tests/test_pca.py
tests/test_preprocessing.py
tests/test_similarity.py
tests/test_utils.py
nd_sim-0.1.0.dist-info/METADATA
nd_sim-0.1.0.dist-info/WHEEL
nd_sim-0.1.0.dist-info/top_level.txt
nd_sim-0.1.0.dist-info/RECORD
