Metadata-Version: 2.1
Name: nd-sim
Version: 0.1.0
Requires-Dist: numpy
Requires-Dist: scipy
Requires-Dist: rdkit
